{
	"all": {
		"meta": {
			"page": 1,
			"resources_per_page": 5,
			"total_resources": 6
		},
		"data": [{
				"type": "orders",
				"id": "1",
				"attributes": {
					"orderId": "12121212",
					"status": "In-Progress",
					"amount": "2000",
					"isRated": false,
					"rating": 0,
					"details": "This order is reference to 1010102 order number and total no of items added is 10",
					"image" : "assets/wash_dry_hung.jpg"
				}
			},
			{
				"type": "orders",
				"id": "2",
				"attributes": {
					"orderId": "11122211",
					"status": "Delivered",
					"amount": "2000",
					"isRated": false,
					"rating": 0,
					"details": "This order is reference to 1010102 order number and total no of items added is 10",
					"image" : "assets/wash_dry_hung.jpg"
				}
			}, {
				"type": "orders",
				"id": "2",
				"attributes": {
					"orderId": "11122211",
					"status": "Delivered",
					"amount": "2000",
					"isRated": true,
					"rating": 4,
					"details": "This order is reference to 1010102 order number and total no of items added is 10,
					"image" : "assets/wash_dry_hung.jpg"
				}
			}
		]
	},
	"meta": {
		"total-records": 2
	},
	"links": {
		"self": "/authors/2"
	}
}
